[
  {
    "date": "2026-06-17",
    "bok_source_date": "2026-06-17",
    "bok_usd_krw": 1513.5,
    "cbr_usd_rub": 72.1388,
    "calc_rub_krw": 20.980388,
    "krw_1_5m_to_rub": 71495,
    "usd_rub": 72.1388,
    "krw_rub": 20.980388,
    "score": 60,
    "signal": "■ NORMAL"
  },
  {
    "date": "2026-06-18",
    "bok_source_date": "2026-06-18",
    "bok_usd_krw": 1512.8,
    "cbr_usd_rub": 72.7479,
    "calc_rub_krw": 20.795102,
    "krw_1_5m_to_rub": 72132,
    "usd_rub": 72.7479,
    "krw_rub": 20.795102,
    "score": 66,
    "signal": "● GOOD"
  },
  {
    "date": "2026-06-19",
    "bok_source_date": "2026-06-19",
    "bok_usd_krw": 1523.4,
    "cbr_usd_rub": 73.3591,
    "calc_rub_krw": 20.76634,
    "krw_1_5m_to_rub": 72232,
    "usd_rub": 73.3591,
    "krw_rub": 20.76634,
    "score": 66,
    "signal": "● GOOD"
  },
  {
    "date": "2026-06-20",
    "bok_source_date": "2026-06-19",
    "bok_usd_krw": 1523.4,
    "cbr_usd_rub": 73.439,
    "calc_rub_krw": 20.743747,
    "krw_1_5m_to_rub": 72311,
    "usd_rub": 73.439,
    "krw_rub": 20.743747,
    "score": 66,
    "signal": "● GOOD"
  },
  {
    "date": "2026-06-21",
    "bok_source_date": "2026-06-19",
    "bok_usd_krw": 1523.4,
    "cbr_usd_rub": 73.439,
    "calc_rub_krw": 20.743747,
    "krw_1_5m_to_rub": 72311,
    "usd_rub": 73.439,
    "krw_rub": 20.743747,
    "score": 65,
    "signal": "● GOOD"
  },
  {
    "date": "2026-06-22",
    "bok_source_date": "2026-06-22",
    "bok_usd_krw": 1535.0,
    "cbr_usd_rub": 73.439,
    "calc_rub_krw": 20.901701,
    "krw_1_5m_to_rub": 71764,
    "usd_rub": 73.439,
    "krw_rub": 20.901701,
    "score": 57,
    "signal": "■ NORMAL"
  },
  {
    "date": "2026-06-23",
    "bok_source_date": "2026-06-23",
    "bok_usd_krw": 1535.7,
    "cbr_usd_rub": 73.765,
    "calc_rub_krw": 20.818817,
    "krw_1_5m_to_rub": 72050,
    "usd_rub": 73.765,
    "krw_rub": 20.818817,
    "score": 62,
    "signal": "■ NORMAL"
  },
  {
    "date": "2026-06-24",
    "bok_source_date": "2026-06-24",
    "bok_usd_krw": 1537.2,
    "cbr_usd_rub": 74.62,
    "calc_rub_krw": 20.600375,
    "krw_1_5m_to_rub": 72814,
    "usd_rub": 74.62,
    "krw_rub": 20.600375,
    "score": 73,
    "signal": "● GOOD"
  },
  {
    "date": "2026-06-25",
    "bok_source_date": "2026-06-25",
    "bok_usd_krw": 1538.3,
    "cbr_usd_rub": 74.7738,
    "calc_rub_krw": 20.572714,
    "krw_1_5m_to_rub": 72912,
    "usd_rub": 74.7738,
    "krw_rub": 20.572714,
    "naver_rub_krw": 7.0,
    "naver_time": "2026.06.25 22:09",
    "naver_cash_buy": 22.3,
    "naver_cash_sell": 16.81,
    "naver_send": 21.08,
    "naver_receive": 19.66,
    "naver_tc_buy": "N/A",
    "naver_check_sell": "N/A",
    "score": 73,
    "signal": "● GOOD"
  },
  {
    "date": "2026-06-26",
    "bok_source_date": "2026-06-26",
    "bok_usd_krw": 1545.3,
    "cbr_usd_rub": 75.6347,
    "calc_rub_krw": 20.431098,
    "krw_1_5m_to_rub": 73417,
    "usd_rub": 75.6347,
    "krw_rub": 20.431098,
    "naver_rub_krw": 19.71,
    "naver_time": "2026.06.26 21:26",
    "naver_cash_buy": 21.58,
    "naver_cash_sell": 16.27,
    "naver_send": 20.39,
    "naver_receive": 19.03,
    "naver_tc_buy": "N/A",
    "naver_check_sell": "N/A",
    "score": 80,
    "signal": "▲ BEST"
  }
]